<?xml version="1.0" encoding="UTF-8" ?>
<languages>
    <language index="en">
	<label index="Generate">Generate</label>
	<label index="Settings">Settings</label>
        <label index="Actions">Actions</label>
	<label index="SEO">SEO</label>
	<label index="SEOTitle">Title and other properties of the current page</label>
        <label index="DeleteDoc">Delete Page</label>
	<label index="DeleteDocTitle">Here you can delete the current page</label>
        <label index="DeleteDocDescription">Do you want to delete the following page?</label>
	<label index="GenerateOne">This</label>
	<label index="GenerateOne2">Generate the current Page</label>
	<label index="GenerateAll">All</label>
	<label index="GenerateAll2">Generate all Pages</label>
	<label index="Close">Close</label>
        <label index="Cancel">Cancel</label>
	<label index="Save">Save</label>
        <label index="Ok">Ok</label>
        <label index="Delete">Delete</label>
	<label index="Publish">The page will be published...</label>
	<label index="Publish2">All pages will be published...</label>
	<label index="Documentpublished">Done!</label>
	<label index="Document">Page</label>
	<label index="FileName">Filename</label>
	<label index="AutoFileName">Automatic Filename</label>
	<label index="AutoFileName2">Yes</label>
	<label index="Title">Title</label>
	<label index="AutoTitle">Automatic Title</label>
	<label index="AutoTitle2">Yes</label>
	<label index="Meta-Description">Meta-Description</label>
	<label index="Meta-Keywords">Meta-Keywords</label>
        <label index="NoTitle">No Title</label>
        <label index="Author">Author</label>
	<label index="LastChange">Last Change</label>
        <label index="Description">Description</label>
        <label index="Content">Content</label>
        <label index="Deleted">Deleted</label>
        <label index="Deleted2">The page has been deleted successfully.</label>
    </language>
    <language index="de">
	<label index="Generate">Veröffentlichen</label>
	<label index="Settings">Einstellungen</label>
        <label index="Actions">Aktionen</label>
	<label index="SEO">Seiten-Titel, Meta-Information</label>
	<label index="SEOTitle">Hier können Sie den Titel und weitere Eigenschaften der aktuellen Seite bearbeiten.</label>
        <label index="DeleteDoc">Seite löschen</label>
	<label index="DeleteDocTitle">Hier können Sie die aktuelle Seite löschen.</label>
        <label index="DeleteDocDescription">Wollen Sie die folgende Seite wirklich löschen?</label>
	<label index="GenerateOne">Die aktuelle Seite</label>
	<label index="GenerateOne2">Die aktuelle Seite veröffentlichen</label>
	<label index="GenerateAll">Alle Seiten</label>
	<label index="GenerateAll2">Alle Seiten veröffentlichen</label>
	<label index="Close">Schließen</label>
        <label index="Cancel">Abbrechen</label>
	<label index="Save">Speichern</label>
        <label index="Ok">Ok</label>
        <label index="Delete">Löschen</label>
	<label index="Publish">Die Seite wird veröffentlicht...</label>
	<label index="Publish2">Alle Seiten werden veröffentlicht...</label>
	<label index="Documentpublished">Fertig!</label>
	<label index="Document">Seite</label>
	<label index="FileName">Dateiname</label>
	<label index="AutoFileName">Dateinamen automatisch setzen?</label>
	<label index="AutoFileName2">Ja</label>
	<label index="Title">Titel</label>
	<label index="AutoTitle">Titel automatisch setzen?</label>
	<label index="AutoTitle2">Ja</label>
	<label index="Meta-Description">Meta-Beschreibung</label>
	<label index="Meta-Keywords">Meta-Schlüsselwöter</label>
        <label index="NoTitle">Kein Titel</label>
        <label index="Author">Autor</label>
	<label index="LastChange">Letzte Änderung</label>
        <label index="Description">Beschreibung</label>
        <label index="Content">Inhalt</label>
        <label index="Deleted">Gelöscht</label>
        <label index="Deleted2">Die Seite wurde erfolgreich gelöscht.</label>
    </language>
</languages>